odoo/addons/web_search_with_and/README.rst
odoo/addons/web_search_with_and/__init__.py
odoo/addons/web_search_with_and/__manifest__.py
odoo/addons/web_search_with_and/i18n/es.po
odoo/addons/web_search_with_and/i18n/it.po
odoo/addons/web_search_with_and/i18n/pt.po
odoo/addons/web_search_with_and/i18n/tr.po
odoo/addons/web_search_with_and/i18n/web_search_with_and.pot
odoo/addons/web_search_with_and/readme/CONTRIBUTORS.md
odoo/addons/web_search_with_and/readme/DESCRIPTION.md
odoo/addons/web_search_with_and/readme/USAGE.md
odoo/addons/web_search_with_and/static/description/icon.png
odoo/addons/web_search_with_and/static/description/index.html
odoo/addons/web_search_with_and/static/src/js/search_bar.esm.js
odoo/addons/web_search_with_and/static/src/js/search_model.esm.js
odoo_addon_web_search_with_and-19.0.1.0.0.2.dist-info/METADATA
odoo_addon_web_search_with_and-19.0.1.0.0.2.dist-info/WHEEL
odoo_addon_web_search_with_and-19.0.1.0.0.2.dist-info/top_level.txt
odoo_addon_web_search_with_and-19.0.1.0.0.2.dist-info/RECORD
