Metadata-Version: 2.1
Name: odoo-addon-web_search_with_and
Version: 19.0.1.0.0.2
Requires-Dist: odoo==19.0.*
Summary: Use AND conditions on omnibar search
Home-page: https://github.com/OCA/web
License: AGPL-3
Author: Sandip SCS, Versada UAB, ACSONE SA/NV, Serincloud, Odoo Community Association (OCA)
Author-email: support@odoo-community.org
Classifier: Programming Language :: Python
Classifier: Framework :: Odoo
Classifier: Framework :: Odoo :: 19.0
Classifier: License :: OSI Approved :: GNU Affero General Public License v3
